cEstimate.so
sshmm/MyHMM.py
sshmm/__init__.py
sshmm/pwm.py
sshmm/seq_hmm.py
sshmm/seqstructhmm.py
sshmm/sequence_container.py
sshmm/setup.py
sshmm/simple_queue.py
sshmm/structure_prediction.py
sshmm/img/A.png
sshmm/img/C.png
sshmm/img/G.png
sshmm/img/T.png
sshmm/img/U.png
sshmm-1.0.0b1.data/scripts/batch_seqstructhmm
sshmm-1.0.0b1.data/scripts/preprocess_dataset
sshmm-1.0.0b1.data/scripts/train_seqstructhmm
sshmm-1.0.0b1.dist-info/DESCRIPTION.rst
sshmm-1.0.0b1.dist-info/METADATA
sshmm-1.0.0b1.dist-info/RECORD
sshmm-1.0.0b1.dist-info/WHEEL
sshmm-1.0.0b1.dist-info/metadata.json
sshmm-1.0.0b1.dist-info/top_level.txt
