Metadata-Version: 2.0
Name: sshmm
Version: 1.0.0b1
Summary: A sequence-structure hidden Markov model for the analysis of RNA-binding protein data.
Home-page: https://github.molgen.mpg.de/heller/ssHMM
Author: David Heller, Annalisa Marsico
Author-email: heller_d@molgen.mpg.de
License: GPLv3
Keywords: sshmm CLIP-Seq RBP RNA RNA-binding protein motif HMM sequence structure
Platform: UNKNOWN
Classifier: Development Status :: 4 - Beta
Classifier: Environment :: Console
Classifier: Intended Audience :: Science/Research
Classifier: Topic :: Scientific/Engineering :: Bio-Informatics
Classifier: License :: OSI Approved :: GNU General Public License v3 (GPLv3)
Classifier: Programming Language :: Python :: 2.7
Requires-Dist: forgi
Requires-Dist: graphviz
Requires-Dist: numpy
Requires-Dist: pygraphviz
Requires-Dist: weblogo
